{
  "headerNavigation": [
    {
      "name": "Home",
      "link": "/",
      "external": false
    },
    {
      "name": "Mission",
      "link": "/mission",
      "external": false
    },
    {
      "name": "Projects",
      "link": "#",
      "children": []
    },
    {
      "name": "Testimonials",
      "link": "/testimonials",
      "external": false
    },
    {
      "name": "About",
      "link": "/about-us",
      "external": false
    },
    {
      "name": "More",
      "link": "#",
      "children": [
        {
          "name": "Theme",
          "link": "https://www.github.com/jammeryhq/gridsome-starter-liebling",
          "external": true
        }
      ]
    }
  ]
}